setup.cfg
setup.py
comicslicer/__init__.py
comicslicer/comicslicer.py
comicslicer.egg-info/PKG-INFO
comicslicer.egg-info/SOURCES.txt
comicslicer.egg-info/dependency_links.txt
comicslicer.egg-info/requires.txt
comicslicer.egg-info/top_level.txt