Metadata-Version: 1.1
Name: comicslicer
Version: 0.0.1
Summary: slices a comic
Home-page: https://github.com/arnehilmann/comicslicer
Author: Arne Hilmann
Author-email: arne.hilmann@t-online.de
License: UNKNOWN
Platform: UNKNOWN
Classifier: Programming Language :: Python
Classifier: Programming Language :: Python :: 2
Classifier: License :: OSI Approved :: GNU General Public License (GPL)
Classifier: Operating System :: OS Independent
Classifier: Development Status :: 3 - Alpha
Classifier: Environment :: Console
Classifier: Intended Audience :: Developers
Classifier: Topic :: Scientific/Engineering :: Image Recognition
Classifier: Topic :: Multimedia :: Graphics :: Graphics Conversion
